mqc/__init__.py
mqc/config.py
mqc/defaults.py
mqc/defaults_id.py
mqc/main.py
mqc/mqcpath_visualization.py
mqc/mqcpath_visualization2.py
mqc/utils.py
mqc/control/__init__.py
mqc/control/atp_control.py
mqc/control/biomass_control.py
mqc/control/check_control.py
mqc/control/initial_control.py
mqc/control/interface.py
mqc/control/model_control.py
mqc/control/nadh_control.py
mqc/control/net_control.py
mqc/control/preprocessing_control.py
mqc/control/quantitative_control.py
mqc/control/rules_control.py
mqc/control/rules_control2.py
mqc/control/yield_control.py
mqc/control/yield_control2.py
mqc/control/__pycache__/.wolf11563301ovEEAfTsIjj.cpython-38.pyc
mqc/control/__pycache__/.wolf1156330bZsu7OdwfgYk.cpython-38.pyc
mqc/control/__pycache__/.wolf1156330cVantTC5K1cT.cpython-38.pyc
mqc/control/__pycache__/__init__.cpython-38.pyc
mqc/control/__pycache__/atp_control.cpython-38.pyc
mqc/control/__pycache__/biomass_control.cpython-38.pyc
mqc/control/__pycache__/check_control.cpython-38.pyc
mqc/control/__pycache__/initial_control.cpython-38.pyc
mqc/control/__pycache__/interface.cpython-38.pyc
mqc/control/__pycache__/model_control.cpython-38.pyc
mqc/control/__pycache__/nadh_control.cpython-38.pyc
mqc/control/__pycache__/net_control.cpython-38.pyc
mqc/control/__pycache__/preprocessing_control.cpython-38.pyc
mqc/control/__pycache__/quantitative_control.cpython-38.pyc
mqc/control/__pycache__/rules_control.cpython-38.pyc
mqc/control/__pycache__/rules_control2.cpython-38.pyc
mqc/control/__pycache__/yield_control.cpython-38.pyc
mqc/control/__pycache__/yield_control2.cpython-38.pyc
mqc/summary/BiGGdata_map.xlsx
mqc/summary/MetacycRule.xlsx
mqc/summary/bigg_metacyc.xlsx
mqc/summary/biolog_bsub.tsv
mqc/summary/biolog_ecol.tsv
mqc/summary/biolog_paer.tsv
mqc/summary/biolog_rsol.tsv
mqc/summary/biolog_sone.tsv
mqc/summary/essential_MOPS_succ.tsv
mqc/summary/essential_glc_mm.csv
mqc/summary/essential_rich_medium.tsv
mqc/summary/essentiality.tsv
mqc/summary/essentiality_price2016.tsv
mqc-5.0.dist-info/LICENSE
mqc-5.0.dist-info/METADATA
mqc-5.0.dist-info/WHEEL
mqc-5.0.dist-info/entry_points.txt
mqc-5.0.dist-info/top_level.txt
mqc-5.0.dist-info/RECORD
