Metadata-Version: 2.1
Name: mqc
Version: 5.0
Summary: MQC is a Genome-scale metabolic network model quality control tool
Home-page: http://172.16.25.29/dengxiao/mqc/
Author: dengxiao
Author-email: dengxg@tib.cas.cn
Classifier: Programming Language :: Python :: 3
Classifier: License :: OSI Approved :: MIT License
Classifier: Operating System :: OS Independent
Requires-Python: >=3.6
License-File: LICENSE
Requires-Dist: httpx ==0.23.0
Requires-Dist: numpy ==1.22.4
Requires-Dist: cobra ==0.25.0
Requires-Dist: matplotlib ==3.7.2
Requires-Dist: d3flux ==0.2.7
Requires-Dist: openpyxl
